stpredict/__init__.py
stpredict/apply_performance_mode.py
stpredict/configurations.py
stpredict/get_future_data.py
stpredict/get_map.py
stpredict/get_normal_target.py
stpredict/get_target_quantities.py
stpredict/get_target_temporal_ids.py
stpredict/get_trivial_values.py
stpredict/models.py
stpredict/one_by_one.py
stpredict/performance.py
stpredict/performance_summary.py
stpredict/plot_prediction.py
stpredict/predict.py
stpredict/predict_func.py
stpredict/predict_future.py
stpredict/preprocess.py
stpredict/rank_covariates.py
stpredict/rank_features.py
stpredict/scaling.py
stpredict/select_features.py
stpredict/sgcrf.py
stpredict/split_data.py
stpredict/train_evaluate.py
stpredict/train_test.py
stpredict/train_validate.py
stpredict/whole_as_one.py
stpredict/data/USA_COVID_19_data.csv
stpredict/data/earthquake_data.csv
stpredict-0.0.12.dist-info/licenses/LICENSE
stpredict-0.0.12.dist-info/METADATA
stpredict-0.0.12.dist-info/WHEEL
stpredict-0.0.12.dist-info/top_level.txt
stpredict-0.0.12.dist-info/RECORD
