Metadata-Version: 2.4
Name: stpredict
Version: 0.0.12
Summary: Spatio-temporal prediction package
Home-page: https://github.com/network-and-Data-Science-IUT/stpredict
Author: Arash Mari Oriyad, Maryam Meghdadi, Mahdi Naderi, Arezoo Haratian
Author-email: arashmarioriyad@gmail.com, arezo.h1371@yahoo.com
Maintainer: cndalab
Maintainer-email: cndalab.iut@gmail.com, pramazi@brocku.ca, arashmarioriyad@gmail.com, arezo.h1371@yahoo.com
Project-URL: Documentation, https://stpredict.readthedocs.io/en/latest/
Classifier: Programming Language :: Python :: 3
Classifier: License :: OSI Approved :: MIT License
Classifier: Operating System :: OS Independent
License-File: LICENSE
Requires-Dist: scikit-learn>=0.24
Requires-Dist: scikeras>=0.13.0
Dynamic: license-file
